[
    {
      "section": "ExtHTMLDocument",
      "type": "SELF_CLOSE_TAG",
      "value": "INPUT",
      "attrs": [
        {
          "name": "type",
          "value": "text",
          "category": "html_attribute",
          "pos": 0
        }
      ],
      "dynamic_attrs": [
        {
          "name": "value",
          "value": "Filter:onlyNumbers;Validation:cpf;Filter:cpf",
          "category": "html_attribute",
          "pos": 1
        },
        {
          "name": "in",
          "value": "DB::person.cpf;Filter:cpf",
          "category": "lang_directive",
          "pos": 2
        },
        {
          "name": "out",
          "value": "DB::person.cpf",
          "category": "lang_directive",
          "pos": 3
        }
      ],
      "event_attrs": [],
      "children": [],
      "location": {
        "start": {
          "offset": 8,
          "line": 1,
          "column": 9
        },
        "end": {
          "offset": 135,
          "line": 1,
          "column": 136
        }
      }
    },
    {
      "section": "ExtHTMLDocument",
      "type": "NEW_LINE",
      "value": [
        "\n"
      ],
      "attrs": [],
      "dynamic_attrs": [],
      "event_attrs": [],
      "children": [],
      "location": {
        "start": {
          "offset": 135,
          "line": 1,
          "column": 136
        },
        "end": {
          "offset": 136,
          "line": 2,
          "column": 1
        }
      }
    },
    {
      "section": "ExtHTMLDocument",
      "type": "TEXT_NODE",
      "value": "        ",
      "attrs": [],
      "event_attrs": [],
      "children": [],
      "location": {
        "start": {
          "offset": 136,
          "line": 2,
          "column": 1
        },
        "end": {
          "offset": 144,
          "line": 2,
          "column": 9
        }
      }
    },
    {
      "section": "ExtHTMLDocument",
      "type": "HTML_NESTED_TAG",
      "value": "BUTTON",
      "attrs": [],
      "dynamic_attrs": [],
      "event_attrs": [
        {
          "name": "click",
          "value": "DB.save()",
          "category": "html_attribute",
          "modifiers": [],
          "mouse_keys": "",
          "keyboard_modifiers_keys": [],
          "pos": 0
        }
      ],
      "children": [
        {
          "section": "ExtHTMLDocument",
          "type": "TEXT_NODE",
          "value": "Save",
          "attrs": [],
          "event_attrs": [],
          "children": [],
          "location": {
            "start": {
              "offset": 171,
              "line": 2,
              "column": 36
            },
            "end": {
              "offset": 175,
              "line": 2,
              "column": 40
            }
          }
        }
      ],
      "location": {
        "start": {
          "offset": 144,
          "line": 2,
          "column": 9
        },
        "end": {
          "offset": 184,
          "line": 2,
          "column": 49
        }
      }
    }
]